[
    {
        "id": "ORD001",
        "customer_name": "Rahul Kumar",
        "address": "Bhatibari Road, Joka, Kolkata-700098",
        "lat": 22.548455,
        "lon": 88.359956,
        "priority": "high",
        "package_size": "medium",
        "fragile": true
    },
    {
        "id": "ORD002",
        "customer_name": "Sita Devi",
        "address": "Kolkata Road, Joka, Kolkata-700098",
        "lat": 22.548743,
        "lon": 88.363235,
        "priority": "medium",
        "package_size": "small",
        "fragile": false
    },
    {
        "id": "ORD003",
        "customer_name": "Ananya Banerjee",
        "address": "Sector V, Salt Lake, Kolkata-700091",
        "lat": 22.612974,
        "lon": 88.344847,
        "priority": "low",
        "package_size": "large",
        "fragile": true
    },
    {
        "id": "ORD004",
        "customer_name": "Kamal Mukherjee",
        "address": "New Town, Salt Lake, Kolkata-700091",
        "lat": 22.631604,
        "lon": 88.439831,
        "priority": "high",
        "package_size": "medium",
        "fragile": false
    },
    {
        "id": "ORD005",
        "customer_name": "Rina Das",
        "address": "Bhatibari Road, Joka, Kolkata-700098",
        "lat": 22.579573,
        "lon": 88.37058,
        "priority": "medium",
        "package_size": "small",
        "fragile": true
    },
    {
        "id": "ORD006",
        "customer_name": "Sourav Roy",
        "address": "Sector 6, New Town, Kolkata-700091",
        "lat": 22.613296,
        "lon": 88.443769,
        "priority": "low",
        "package_size": "medium",
        "fragile": false
    },
    {
        "id": "ORD007",
        "customer_name": "Mina Saha",
        "address": "Joka, Bhatibari, Kolkata-700098",
        "lat": 22.594051,
        "lon": 88.368881,
        "priority": "high",
        "package_size": "large",
        "fragile": true
    },
    {
        "id": "ORD008",
        "customer_name": "Abhijit Bose",
        "address": "Joka, Bhatibari, Kolkata-700098",
        "lat": 22.602422,
        "lon": 88.375596,
        "priority": "medium",
        "package_size": "small",
        "fragile": false
    },
    {
        "id": "ORD009",
        "customer_name": "Pooja Patel",
        "address": "New Town, Salt Lake, Kolkata-700091",
        "lat": 22.570057,
        "lon": 88.413227,
        "priority": "low",
        "package_size": "medium",
        "fragile": true
    },
    {
        "id": "ORD010",
        "customer_name": "Dipak Ghosh",
        "address": "Joka, Bhatibari, Kolkata-700098",
        "lat": 22.510354,
        "lon": 88.372622,
        "priority": "high",
        "package_size": "large",
        "fragile": false
    },
    {
        "id": "ORD011",
        "customer_name": "Rohit Sharma",
        "address": "New Town, Salt Lake, Kolkata-700091",
        "lat": 22.539717,
        "lon": 88.441279,
        "priority": "medium",
        "package_size": "small",
        "fragile": true
    }
]